symetry/__init__.py
symetry/cli.py
symetry/commons/__init__.py
symetry/core/__init__.py
symetry-1.0.0.dist-info/LICENSE
symetry-1.0.0.dist-info/METADATA
symetry-1.0.0.dist-info/WHEEL
symetry-1.0.0.dist-info/entry_points.txt
symetry-1.0.0.dist-info/top_level.txt
symetry-1.0.0.dist-info/RECORD
