Metadata-Version: 2.1
Name: symetry
Version: 1.0.0
Summary: Symetry is web development framework.
Home-page: https://github.com/stacknix/symetry
Author: Ashish Sahu
Author-email: spiraldeveloper@gmail.com
License: MIT
Keywords: python package symetry
Platform: UNKNOWN
Classifier: Programming Language :: Python :: 3
Classifier: License :: OSI Approved :: MIT License
Classifier: Operating System :: OS Independent
License-File: LICENSE
Requires-Dist: psycopg2-binary (==2.9.3)
Requires-Dist: gunicorn (==20.1.0)
Requires-Dist: Jinja2 (==3.1.2)
Requires-Dist: requests (==2.28.1)
Requires-Dist: redis (==4.3.4)
Requires-Dist: celery (==5.2.7)
Requires-Dist: flower (==1.1.0)
Requires-Dist: click (==8.1.3)
Requires-Dist: bcrypt (==3.2.2)
Requires-Dist: cryptography (==37.0.4)
